{"type":"FeatureCollection","crs":{"type":"name","properties":{"name":"EPSG:4326"}},"features":[{"type":"Feature","id":1,"geometry":{"type":"Point","coordinates":[47.6000000014901,-14.1000000014901]},"properties":{"OBJECTID":1,"STORMNAME":"Gamane","STORMTYPE":" ","ADVDATE":1711632300000,"ADVISNUM":" ","STORMNUM":20,"FCSTPRD":72,"BASIN":"SH","LAT":-14.1,"LON":47.6,"VALIDTIME":"28/1200","TAU":0,"MAXWIND":30,"GUST":0,"MSLP":0,"TCDVLP":"Tropical Depression","DVLBL":"D","SSNUM":0,"TCDIR":0,"TCSPD":0,"DATELBL":"12:00 PM Thu","FLDATELBL":"2024-03-28 12:00 PM Thu UTC","TIMEZONE":"UTC","STORMSRC":" "}},{"type":"Feature","id":2,"geometry":{"type":"Point","coordinates":[48.6000000014901,-15]},"properties":{"OBJECTID":2,"STORMNAME":"Gamane","STORMTYPE":" ","ADVDATE":1711632300000,"ADVISNUM":" ","STORMNUM":20,"FCSTPRD":72,"BASIN":"SH","LAT":-15,"LON":48.6,"VALIDTIME":"29/0000","TAU":0,"MAXWIND":25,"GUST":0,"MSLP":9999,"TCDVLP":"Tropical Depression","DVLBL":"D","SSNUM":0,"TCDIR":9999,"TCSPD":9999,"DATELBL":"12:00 AM Fri","FLDATELBL":"2024-03-29 12:00 AM Fri UTC","TIMEZONE":"UTC","STORMSRC":" "}},{"type":"Feature","id":3,"geometry":{"type":"Point","coordinates":[49.6000000014901,-15.8999999985099]},"properties":{"OBJECTID":3,"STORMNAME":"Gamane","STORMTYPE":" ","ADVDATE":1711632300000,"ADVISNUM":" ","STORMNUM":20,"FCSTPRD":72,"BASIN":"SH","LAT":-15.9,"LON":49.6,"VALIDTIME":"29/1200","TAU":0,"MAXWIND":25,"GUST":0,"MSLP":9999,"TCDVLP":"Tropical Depression","DVLBL":"D","SSNUM":0,"TCDIR":9999,"TCSPD":9999,"DATELBL":"12:00 PM Fri","FLDATELBL":"2024-03-29 12:00 PM Fri UTC","TIMEZONE":"UTC","STORMSRC":" "}},{"type":"Feature","id":4,"geometry":{"type":"Point","coordinates":[50.8000000007451,-16.8999999985099]},"properties":{"OBJECTID":4,"STORMNAME":"Gamane","STORMTYPE":" ","ADVDATE":1711632300000,"ADVISNUM":" ","STORMNUM":20,"FCSTPRD":72,"BASIN":"SH","LAT":-16.9,"LON":50.8,"VALIDTIME":"30/0000","TAU":0,"MAXWIND":30,"GUST":0,"MSLP":9999,"TCDVLP":"Tropical Depression","DVLBL":"D","SSNUM":0,"TCDIR":9999,"TCSPD":9999,"DATELBL":"12:00 AM Sat","FLDATELBL":"2024-03-30 12:00 AM Sat UTC","TIMEZONE":"UTC","STORMSRC":" "}},{"type":"Feature","id":5,"geometry":{"type":"Point","coordinates":[52.1999999992549,-17.6999999992549]},"properties":{"OBJECTID":5,"STORMNAME":"Gamane","STORMTYPE":" ","ADVDATE":1711632300000,"ADVISNUM":" ","STORMNUM":20,"FCSTPRD":72,"BASIN":"SH","LAT":-17.7,"LON":52.2,"VALIDTIME":"30/1200","TAU":0,"MAXWIND":35,"GUST":0,"MSLP":9999,"TCDVLP":"Tropical Storm","DVLBL":"S","SSNUM":0,"TCDIR":9999,"TCSPD":9999,"DATELBL":"12:00 PM Sat","FLDATELBL":"2024-03-30 12:00 PM Sat UTC","TIMEZONE":"UTC","STORMSRC":" "}},{"type":"Feature","id":6,"geometry":{"type":"Point","coordinates":[54.6000000014901,-18.1000000014901]},"properties":{"OBJECTID":6,"STORMNAME":"Gamane","STORMTYPE":" ","ADVDATE":1711632300000,"ADVISNUM":" ","STORMNUM":20,"FCSTPRD":72,"BASIN":"SH","LAT":-18.1,"LON":54.6,"VALIDTIME":"31/1200","TAU":0,"MAXWIND":30,"GUST":0,"MSLP":9999,"TCDVLP":"Tropical Depression","DVLBL":"D","SSNUM":0,"TCDIR":9999,"TCSPD":9999,"DATELBL":"12:00 PM Sun","FLDATELBL":"2024-03-31 12:00 PM Sun UTC","TIMEZONE":"UTC","STORMSRC":" "}}]}