{"type":"FeatureCollection","crs":{"type":"name","properties":{"name":"EPSG:4326"}},"features":[{"type":"Feature","id":1,"geometry":{"type":"Point","coordinates":[125.699999999255,17]},"properties":{"OBJECTID":1,"STORMNAME":"Gaemi","STORMTYPE":" ","ADVDATE":1721592600000,"ADVISNUM":" ","STORMNUM":5,"FCSTPRD":72,"BASIN":"WP","LAT":17,"LON":125.7,"VALIDTIME":"21/1800","TAU":0,"MAXWIND":55,"GUST":0,"MSLP":0,"TCDVLP":"Tropical Storm","DVLBL":"S","SSNUM":0,"TCDIR":0,"TCSPD":0,"DATELBL":"06:00 PM Sun","FLDATELBL":"2024-07-21 06:00 PM Sun UTC","TIMEZONE":"UTC","STORMSRC":" "}},{"type":"Feature","id":2,"geometry":{"type":"Point","coordinates":[125.699999999255,17.6000000014901]},"properties":{"OBJECTID":2,"STORMNAME":"Gaemi","STORMTYPE":" ","ADVDATE":1721592600000,"ADVISNUM":" ","STORMNUM":5,"FCSTPRD":72,"BASIN":"WP","LAT":17.6,"LON":125.7,"VALIDTIME":"22/0600","TAU":0,"MAXWIND":60,"GUST":0,"MSLP":9999,"TCDVLP":"Tropical Storm","DVLBL":"S","SSNUM":0,"TCDIR":9999,"TCSPD":9999,"DATELBL":"06:00 AM Mon","FLDATELBL":"2024-07-22 06:00 AM Mon UTC","TIMEZONE":"UTC","STORMSRC":" "}},{"type":"Feature","id":3,"geometry":{"type":"Point","coordinates":[125.60000000149,18.6000000014901]},"properties":{"OBJECTID":3,"STORMNAME":"Gaemi","STORMTYPE":" ","ADVDATE":1721592600000,"ADVISNUM":" ","STORMNUM":5,"FCSTPRD":72,"BASIN":"WP","LAT":18.6,"LON":125.6,"VALIDTIME":"22/1800","TAU":0,"MAXWIND":65,"GUST":0,"MSLP":9999,"TCDVLP":"Hurricane","DVLBL":"H","SSNUM":1,"TCDIR":9999,"TCSPD":9999,"DATELBL":"06:00 PM Mon","FLDATELBL":"2024-07-22 06:00 PM Mon UTC","TIMEZONE":"UTC","STORMSRC":" "}},{"type":"Feature","id":4,"geometry":{"type":"Point","coordinates":[125.5,20.1000000014901]},"properties":{"OBJECTID":4,"STORMNAME":"Gaemi","STORMTYPE":" ","ADVDATE":1721592600000,"ADVISNUM":" ","STORMNUM":5,"FCSTPRD":72,"BASIN":"WP","LAT":20.1,"LON":125.5,"VALIDTIME":"23/0600","TAU":0,"MAXWIND":75,"GUST":0,"MSLP":9999,"TCDVLP":"Hurricane","DVLBL":"H","SSNUM":1,"TCDIR":9999,"TCSPD":9999,"DATELBL":"06:00 AM Tue","FLDATELBL":"2024-07-23 06:00 AM Tue UTC","TIMEZONE":"UTC","STORMSRC":" "}},{"type":"Feature","id":5,"geometry":{"type":"Point","coordinates":[125.10000000149,21.8999999985099]},"properties":{"OBJECTID":5,"STORMNAME":"Gaemi","STORMTYPE":" ","ADVDATE":1721592600000,"ADVISNUM":" ","STORMNUM":5,"FCSTPRD":72,"BASIN":"WP","LAT":21.9,"LON":125.1,"VALIDTIME":"23/1800","TAU":0,"MAXWIND":95,"GUST":0,"MSLP":9999,"TCDVLP":"Hurricane","DVLBL":"H","SSNUM":2,"TCDIR":9999,"TCSPD":9999,"DATELBL":"06:00 PM Tue","FLDATELBL":"2024-07-23 06:00 PM Tue UTC","TIMEZONE":"UTC","STORMSRC":" "}},{"type":"Feature","id":6,"geometry":{"type":"Point","coordinates":[123.199999999255,24.6000000014901]},"properties":{"OBJECTID":6,"STORMNAME":"Gaemi","STORMTYPE":" ","ADVDATE":1721592600000,"ADVISNUM":" ","STORMNUM":5,"FCSTPRD":72,"BASIN":"WP","LAT":24.6,"LON":123.2,"VALIDTIME":"24/1800","TAU":0,"MAXWIND":95,"GUST":0,"MSLP":9999,"TCDVLP":"Hurricane","DVLBL":"H","SSNUM":2,"TCDIR":9999,"TCSPD":9999,"DATELBL":"06:00 PM Wed","FLDATELBL":"2024-07-24 06:00 PM Wed UTC","TIMEZONE":"UTC","STORMSRC":" "}},{"type":"Feature","id":7,"geometry":{"type":"Point","coordinates":[120.10000000149,26.5]},"properties":{"OBJECTID":7,"STORMNAME":"Gaemi","STORMTYPE":" ","ADVDATE":1721592600000,"ADVISNUM":" ","STORMNUM":5,"FCSTPRD":72,"BASIN":"WP","LAT":26.5,"LON":120.1,"VALIDTIME":"25/1800","TAU":0,"MAXWIND":65,"GUST":0,"MSLP":9999,"TCDVLP":"Hurricane","DVLBL":"H","SSNUM":1,"TCDIR":9999,"TCSPD":9999,"DATELBL":"06:00 PM Thu","FLDATELBL":"2024-07-25 06:00 PM Thu UTC","TIMEZONE":"UTC","STORMSRC":" "}},{"type":"Feature","id":8,"geometry":{"type":"Point","coordinates":[117.699999999255,29.5]},"properties":{"OBJECTID":8,"STORMNAME":"Gaemi","STORMTYPE":" ","ADVDATE":1721592600000,"ADVISNUM":" ","STORMNUM":5,"FCSTPRD":120,"BASIN":"WP","LAT":29.5,"LON":117.7,"VALIDTIME":"26/1800","TAU":0,"MAXWIND":30,"GUST":0,"MSLP":9999,"TCDVLP":"Tropical Depression","DVLBL":"D","SSNUM":0,"TCDIR":9999,"TCSPD":9999,"DATELBL":"06:00 PM Fri","FLDATELBL":"2024-07-26 06:00 PM Fri UTC","TIMEZONE":"UTC","STORMSRC":" "}},{"type":"Feature","id":9,"geometry":{"type":"Point","coordinates":[110.199999999255,18.8000000007451]},"properties":{"OBJECTID":9,"STORMNAME":"Prapiroon","STORMTYPE":" ","ADVDATE":1721589900000,"ADVISNUM":" ","STORMNUM":4,"FCSTPRD":72,"BASIN":"WP","LAT":18.8,"LON":110.2,"VALIDTIME":"21/1800","TAU":0,"MAXWIND":50,"GUST":0,"MSLP":0,"TCDVLP":"Tropical Storm","DVLBL":"S","SSNUM":0,"TCDIR":0,"TCSPD":0,"DATELBL":"06:00 PM Sun","FLDATELBL":"2024-07-21 06:00 PM Sun UTC","TIMEZONE":"UTC","STORMSRC":" "}},{"type":"Feature","id":10,"geometry":{"type":"Point","coordinates":[109.199999999255,20.1000000014901]},"properties":{"OBJECTID":10,"STORMNAME":"Prapiroon","STORMTYPE":" ","ADVDATE":1721589900000,"ADVISNUM":" ","STORMNUM":4,"FCSTPRD":72,"BASIN":"WP","LAT":20.1,"LON":109.2,"VALIDTIME":"22/0600","TAU":0,"MAXWIND":40,"GUST":0,"MSLP":9999,"TCDVLP":"Tropical Storm","DVLBL":"S","SSNUM":0,"TCDIR":9999,"TCSPD":9999,"DATELBL":"06:00 AM Mon","FLDATELBL":"2024-07-22 06:00 AM Mon UTC","TIMEZONE":"UTC","STORMSRC":" "}},{"type":"Feature","id":11,"geometry":{"type":"Point","coordinates":[108.5,21.1000000014901]},"properties":{"OBJECTID":11,"STORMNAME":"Prapiroon","STORMTYPE":" ","ADVDATE":1721589900000,"ADVISNUM":" ","STORMNUM":4,"FCSTPRD":72,"BASIN":"WP","LAT":21.1,"LON":108.5,"VALIDTIME":"22/1800","TAU":0,"MAXWIND":40,"GUST":0,"MSLP":9999,"TCDVLP":"Tropical Storm","DVLBL":"S","SSNUM":0,"TCDIR":9999,"TCSPD":9999,"DATELBL":"06:00 PM Mon","FLDATELBL":"2024-07-22 06:00 PM Mon UTC","TIMEZONE":"UTC","STORMSRC":" "}},{"type":"Feature","id":12,"geometry":{"type":"Point","coordinates":[108.199999999255,21.8999999985099]},"properties":{"OBJECTID":12,"STORMNAME":"Prapiroon","STORMTYPE":" ","ADVDATE":1721589900000,"ADVISNUM":" ","STORMNUM":4,"FCSTPRD":72,"BASIN":"WP","LAT":21.9,"LON":108.2,"VALIDTIME":"23/0600","TAU":0,"MAXWIND":35,"GUST":0,"MSLP":9999,"TCDVLP":"Tropical Storm","DVLBL":"S","SSNUM":0,"TCDIR":9999,"TCSPD":9999,"DATELBL":"06:00 AM Tue","FLDATELBL":"2024-07-23 06:00 AM Tue UTC","TIMEZONE":"UTC","STORMSRC":" "}},{"type":"Feature","id":13,"geometry":{"type":"Point","coordinates":[107.699999999255,22.1999999992549]},"properties":{"OBJECTID":13,"STORMNAME":"Prapiroon","STORMTYPE":" ","ADVDATE":1721589900000,"ADVISNUM":" ","STORMNUM":4,"FCSTPRD":72,"BASIN":"WP","LAT":22.2,"LON":107.7,"VALIDTIME":"23/1800","TAU":0,"MAXWIND":25,"GUST":0,"MSLP":9999,"TCDVLP":"Tropical Depression","DVLBL":"D","SSNUM":0,"TCDIR":9999,"TCSPD":9999,"DATELBL":"06:00 PM Tue","FLDATELBL":"2024-07-23 06:00 PM Tue UTC","TIMEZONE":"UTC","STORMSRC":" "}},{"type":"Feature","id":14,"geometry":{"type":"Point","coordinates":[107.39999999851,21.6000000014901]},"properties":{"OBJECTID":14,"STORMNAME":"Prapiroon","STORMTYPE":" ","ADVDATE":1721589900000,"ADVISNUM":" ","STORMNUM":4,"FCSTPRD":72,"BASIN":"WP","LAT":21.6,"LON":107.4,"VALIDTIME":"24/1800","TAU":0,"MAXWIND":20,"GUST":0,"MSLP":9999,"TCDVLP":"Tropical Depression","DVLBL":"D","SSNUM":0,"TCDIR":9999,"TCSPD":9999,"DATELBL":"06:00 PM Wed","FLDATELBL":"2024-07-24 06:00 PM Wed UTC","TIMEZONE":"UTC","STORMSRC":" "}}]}