{"type":"FeatureCollection","crs":{"type":"name","properties":{"name":"EPSG:4326"}},"features":[{"type":"Feature","id":1,"geometry":{"type":"Point","coordinates":[80.8000000007451,13.8000000007451]},"properties":{"OBJECTID":1,"STORMNAME":"Michaung","STORMTYPE":" ","ADVDATE":1701698100000,"ADVISNUM":" ","STORMNUM":8,"FCSTPRD":72,"BASIN":"IO","LAT":13.8,"LON":80.8,"VALIDTIME":"04/1200","TAU":0,"MAXWIND":60,"GUST":0,"MSLP":0,"TCDVLP":"Tropical Storm","DVLBL":"S","SSNUM":0,"TCDIR":0,"TCSPD":0,"DATELBL":"12:00 PM Mon","FLDATELBL":"2023-12-04 12:00 PM Mon UTC","TIMEZONE":"UTC","STORMSRC":" "}},{"type":"Feature","id":2,"geometry":{"type":"Point","coordinates":[80.3999999985099,14.8000000007451]},"properties":{"OBJECTID":2,"STORMNAME":"Michaung","STORMTYPE":" ","ADVDATE":1701698100000,"ADVISNUM":" ","STORMNUM":8,"FCSTPRD":72,"BASIN":"IO","LAT":14.8,"LON":80.4,"VALIDTIME":"05/0000","TAU":0,"MAXWIND":65,"GUST":0,"MSLP":9999,"TCDVLP":"Hurricane","DVLBL":"H","SSNUM":1,"TCDIR":9999,"TCSPD":9999,"DATELBL":"12:00 AM Tue","FLDATELBL":"2023-12-05 12:00 AM Tue UTC","TIMEZONE":"UTC","STORMSRC":" "}},{"type":"Feature","id":3,"geometry":{"type":"Point","coordinates":[80.3000000007451,15.6999999992549]},"properties":{"OBJECTID":3,"STORMNAME":"Michaung","STORMTYPE":" ","ADVDATE":1701698100000,"ADVISNUM":" ","STORMNUM":8,"FCSTPRD":72,"BASIN":"IO","LAT":15.7,"LON":80.3,"VALIDTIME":"05/1200","TAU":0,"MAXWIND":55,"GUST":0,"MSLP":9999,"TCDVLP":"Tropical Storm","DVLBL":"S","SSNUM":0,"TCDIR":9999,"TCSPD":9999,"DATELBL":"12:00 PM Tue","FLDATELBL":"2023-12-05 12:00 PM Tue UTC","TIMEZONE":"UTC","STORMSRC":" "}},{"type":"Feature","id":4,"geometry":{"type":"Point","coordinates":[80.3000000007451,16.6999999992549]},"properties":{"OBJECTID":4,"STORMNAME":"Michaung","STORMTYPE":" ","ADVDATE":1701698100000,"ADVISNUM":" ","STORMNUM":8,"FCSTPRD":72,"BASIN":"IO","LAT":16.7,"LON":80.3,"VALIDTIME":"06/0000","TAU":0,"MAXWIND":40,"GUST":0,"MSLP":9999,"TCDVLP":"Tropical Storm","DVLBL":"S","SSNUM":0,"TCDIR":9999,"TCSPD":9999,"DATELBL":"12:00 AM Wed","FLDATELBL":"2023-12-06 12:00 AM Wed UTC","TIMEZONE":"UTC","STORMSRC":" "}},{"type":"Feature","id":5,"geometry":{"type":"Point","coordinates":[80.5,17.8999999985099]},"properties":{"OBJECTID":5,"STORMNAME":"Michaung","STORMTYPE":" ","ADVDATE":1701698100000,"ADVISNUM":" ","STORMNUM":8,"FCSTPRD":72,"BASIN":"IO","LAT":17.9,"LON":80.5,"VALIDTIME":"06/1200","TAU":0,"MAXWIND":30,"GUST":0,"MSLP":9999,"TCDVLP":"Tropical Depression","DVLBL":"D","SSNUM":0,"TCDIR":9999,"TCSPD":9999,"DATELBL":"12:00 PM Wed","FLDATELBL":"2023-12-06 12:00 PM Wed UTC","TIMEZONE":"UTC","STORMSRC":" "}}]}