{"type":"FeatureCollection","crs":{"type":"name","properties":{"name":"EPSG:4326"}},"features":[{"type":"Feature","id":1,"geometry":{"type":"Point","coordinates":[131.10000000149,23.3999999985099]},"properties":{"OBJECTID":1,"STORMNAME":"Khanun","STORMTYPE":" ","ADVDATE":1690809900000,"ADVISNUM":" ","STORMNUM":6,"FCSTPRD":72,"BASIN":"WP","LAT":23.4,"LON":131.1,"VALIDTIME":"31/1200","TAU":0,"MAXWIND":115,"GUST":0,"MSLP":0,"TCDVLP":"Major Hurricane","DVLBL":"M","SSNUM":4,"TCDIR":0,"TCSPD":0,"DATELBL":"12:00 PM Mon","FLDATELBL":"2023-07-31 12:00 PM Mon UTC","TIMEZONE":"UTC","STORMSRC":" "}},{"type":"Feature","id":2,"geometry":{"type":"Point","coordinates":[129.699999999255,24.3999999985099]},"properties":{"OBJECTID":2,"STORMNAME":"Khanun","STORMTYPE":" ","ADVDATE":1690809900000,"ADVISNUM":" ","STORMNUM":6,"FCSTPRD":72,"BASIN":"WP","LAT":24.4,"LON":129.7,"VALIDTIME":"01/0000","TAU":0,"MAXWIND":120,"GUST":0,"MSLP":9999,"TCDVLP":"Major Hurricane","DVLBL":"M","SSNUM":4,"TCDIR":9999,"TCSPD":9999,"DATELBL":"12:00 AM Tue","FLDATELBL":"2023-08-01 12:00 AM Tue UTC","TIMEZONE":"UTC","STORMSRC":" "}},{"type":"Feature","id":3,"geometry":{"type":"Point","coordinates":[128.300000000745,25.1000000014901]},"properties":{"OBJECTID":3,"STORMNAME":"Khanun","STORMTYPE":" ","ADVDATE":1690809900000,"ADVISNUM":" ","STORMNUM":6,"FCSTPRD":72,"BASIN":"WP","LAT":25.1,"LON":128.3,"VALIDTIME":"01/1200","TAU":0,"MAXWIND":120,"GUST":0,"MSLP":9999,"TCDVLP":"Major Hurricane","DVLBL":"M","SSNUM":4,"TCDIR":9999,"TCSPD":9999,"DATELBL":"12:00 PM Tue","FLDATELBL":"2023-08-01 12:00 PM Tue UTC","TIMEZONE":"UTC","STORMSRC":" "}},{"type":"Feature","id":4,"geometry":{"type":"Point","coordinates":[127.199999999255,25.6000000014901]},"properties":{"OBJECTID":4,"STORMNAME":"Khanun","STORMTYPE":" ","ADVDATE":1690809900000,"ADVISNUM":" ","STORMNUM":6,"FCSTPRD":72,"BASIN":"WP","LAT":25.6,"LON":127.2,"VALIDTIME":"02/0000","TAU":0,"MAXWIND":115,"GUST":0,"MSLP":9999,"TCDVLP":"Major Hurricane","DVLBL":"M","SSNUM":4,"TCDIR":9999,"TCSPD":9999,"DATELBL":"12:00 AM Wed","FLDATELBL":"2023-08-02 12:00 AM Wed UTC","TIMEZONE":"UTC","STORMSRC":" "}},{"type":"Feature","id":5,"geometry":{"type":"Point","coordinates":[126.39999999851,26.1000000014901]},"properties":{"OBJECTID":5,"STORMNAME":"Khanun","STORMTYPE":" ","ADVDATE":1690809900000,"ADVISNUM":" ","STORMNUM":6,"FCSTPRD":72,"BASIN":"WP","LAT":26.1,"LON":126.4,"VALIDTIME":"02/1200","TAU":0,"MAXWIND":105,"GUST":0,"MSLP":9999,"TCDVLP":"Major Hurricane","DVLBL":"M","SSNUM":3,"TCDIR":9999,"TCSPD":9999,"DATELBL":"12:00 PM Wed","FLDATELBL":"2023-08-02 12:00 PM Wed UTC","TIMEZONE":"UTC","STORMSRC":" "}},{"type":"Feature","id":6,"geometry":{"type":"Point","coordinates":[125.5,26.8000000007451]},"properties":{"OBJECTID":6,"STORMNAME":"Khanun","STORMTYPE":" ","ADVDATE":1690809900000,"ADVISNUM":" ","STORMNUM":6,"FCSTPRD":72,"BASIN":"WP","LAT":26.8,"LON":125.5,"VALIDTIME":"03/1200","TAU":0,"MAXWIND":85,"GUST":0,"MSLP":9999,"TCDVLP":"Hurricane","DVLBL":"H","SSNUM":2,"TCDIR":9999,"TCSPD":9999,"DATELBL":"12:00 PM Thu","FLDATELBL":"2023-08-03 12:00 PM Thu UTC","TIMEZONE":"UTC","STORMSRC":" "}},{"type":"Feature","id":7,"geometry":{"type":"Point","coordinates":[125.699999999255,27.6000000014901]},"properties":{"OBJECTID":7,"STORMNAME":"Khanun","STORMTYPE":" ","ADVDATE":1690809900000,"ADVISNUM":" ","STORMNUM":6,"FCSTPRD":72,"BASIN":"WP","LAT":27.6,"LON":125.7,"VALIDTIME":"04/1200","TAU":0,"MAXWIND":70,"GUST":0,"MSLP":9999,"TCDVLP":"Hurricane","DVLBL":"H","SSNUM":1,"TCDIR":9999,"TCSPD":9999,"DATELBL":"12:00 PM Fri","FLDATELBL":"2023-08-04 12:00 PM Fri UTC","TIMEZONE":"UTC","STORMSRC":" "}},{"type":"Feature","id":8,"geometry":{"type":"Point","coordinates":[126.5,28.3000000007451]},"properties":{"OBJECTID":8,"STORMNAME":"Khanun","STORMTYPE":" ","ADVDATE":1690809900000,"ADVISNUM":" ","STORMNUM":6,"FCSTPRD":120,"BASIN":"WP","LAT":28.3,"LON":126.5,"VALIDTIME":"05/1200","TAU":0,"MAXWIND":65,"GUST":0,"MSLP":9999,"TCDVLP":"Hurricane","DVLBL":"H","SSNUM":1,"TCDIR":9999,"TCSPD":9999,"DATELBL":"12:00 PM Sat","FLDATELBL":"2023-08-05 12:00 PM Sat UTC","TIMEZONE":"UTC","STORMSRC":" "}}]}