{"type":"FeatureCollection","crs":{"type":"name","properties":{"name":"EPSG:4326"}},"features":[{"type":"Feature","id":1,"geometry":{"type":"Point","coordinates":[57.1000000014901,-13.5]},"properties":{"OBJECTID":1,"STORMNAME":"Dikeledi","STORMTYPE":" ","ADVDATE":1736495700000,"ADVISNUM":" ","STORMNUM":7,"FCSTPRD":72,"BASIN":"SH","LAT":-13.5,"LON":57.1,"VALIDTIME":"10/0600","TAU":0,"MAXWIND":50,"GUST":0,"MSLP":0,"TCDVLP":"Tropical Storm","DVLBL":"S","SSNUM":0,"TCDIR":0,"TCSPD":0,"DATELBL":"06:00 AM Fri","FLDATELBL":"2025-01-10 06:00 AM Fri UTC","TIMEZONE":"UTC","STORMSRC":" "}},{"type":"Feature","id":2,"geometry":{"type":"Point","coordinates":[54.1000000014901,-13]},"properties":{"OBJECTID":2,"STORMNAME":"Dikeledi","STORMTYPE":" ","ADVDATE":1736495700000,"ADVISNUM":" ","STORMNUM":7,"FCSTPRD":72,"BASIN":"SH","LAT":-13,"LON":54.1,"VALIDTIME":"10/1800","TAU":0,"MAXWIND":60,"GUST":0,"MSLP":9999,"TCDVLP":"Tropical Storm","DVLBL":"S","SSNUM":0,"TCDIR":9999,"TCSPD":9999,"DATELBL":"06:00 PM Fri","FLDATELBL":"2025-01-10 06:00 PM Fri UTC","TIMEZONE":"UTC","STORMSRC":" "}},{"type":"Feature","id":3,"geometry":{"type":"Point","coordinates":[51.5,-12.6000000014901]},"properties":{"OBJECTID":3,"STORMNAME":"Dikeledi","STORMTYPE":" ","ADVDATE":1736495700000,"ADVISNUM":" ","STORMNUM":7,"FCSTPRD":72,"BASIN":"SH","LAT":-12.6,"LON":51.5,"VALIDTIME":"11/0600","TAU":0,"MAXWIND":65,"GUST":0,"MSLP":9999,"TCDVLP":"Hurricane","DVLBL":"H","SSNUM":1,"TCDIR":9999,"TCSPD":9999,"DATELBL":"06:00 AM Sat","FLDATELBL":"2025-01-11 06:00 AM Sat UTC","TIMEZONE":"UTC","STORMSRC":" "}},{"type":"Feature","id":4,"geometry":{"type":"Point","coordinates":[49.1000000014901,-12.5]},"properties":{"OBJECTID":4,"STORMNAME":"Dikeledi","STORMTYPE":" ","ADVDATE":1736495700000,"ADVISNUM":" ","STORMNUM":7,"FCSTPRD":72,"BASIN":"SH","LAT":-12.5,"LON":49.1,"VALIDTIME":"11/1800","TAU":0,"MAXWIND":55,"GUST":0,"MSLP":9999,"TCDVLP":"Tropical Storm","DVLBL":"S","SSNUM":0,"TCDIR":9999,"TCSPD":9999,"DATELBL":"06:00 PM Sat","FLDATELBL":"2025-01-11 06:00 PM Sat UTC","TIMEZONE":"UTC","STORMSRC":" "}},{"type":"Feature","id":5,"geometry":{"type":"Point","coordinates":[46.6999999992549,-13.1000000014901]},"properties":{"OBJECTID":5,"STORMNAME":"Dikeledi","STORMTYPE":" ","ADVDATE":1736495700000,"ADVISNUM":" ","STORMNUM":7,"FCSTPRD":72,"BASIN":"SH","LAT":-13.1,"LON":46.7,"VALIDTIME":"12/0600","TAU":0,"MAXWIND":50,"GUST":0,"MSLP":9999,"TCDVLP":"Tropical Storm","DVLBL":"S","SSNUM":0,"TCDIR":9999,"TCSPD":9999,"DATELBL":"06:00 AM Sun","FLDATELBL":"2025-01-12 06:00 AM Sun UTC","TIMEZONE":"UTC","STORMSRC":" "}},{"type":"Feature","id":6,"geometry":{"type":"Point","coordinates":[43,-15]},"properties":{"OBJECTID":6,"STORMNAME":"Dikeledi","STORMTYPE":" ","ADVDATE":1736495700000,"ADVISNUM":" ","STORMNUM":7,"FCSTPRD":72,"BASIN":"SH","LAT":-15,"LON":43,"VALIDTIME":"13/0600","TAU":0,"MAXWIND":55,"GUST":0,"MSLP":9999,"TCDVLP":"Tropical Storm","DVLBL":"S","SSNUM":0,"TCDIR":9999,"TCSPD":9999,"DATELBL":"06:00 AM Mon","FLDATELBL":"2025-01-13 06:00 AM Mon UTC","TIMEZONE":"UTC","STORMSRC":" "}},{"type":"Feature","id":7,"geometry":{"type":"Point","coordinates":[40.8000000007451,-17.6000000014901]},"properties":{"OBJECTID":7,"STORMNAME":"Dikeledi","STORMTYPE":" ","ADVDATE":1736495700000,"ADVISNUM":" ","STORMNUM":7,"FCSTPRD":72,"BASIN":"SH","LAT":-17.6,"LON":40.8,"VALIDTIME":"14/0600","TAU":0,"MAXWIND":60,"GUST":0,"MSLP":9999,"TCDVLP":"Tropical Storm","DVLBL":"S","SSNUM":0,"TCDIR":9999,"TCSPD":9999,"DATELBL":"06:00 AM Tue","FLDATELBL":"2025-01-14 06:00 AM Tue UTC","TIMEZONE":"UTC","STORMSRC":" "}},{"type":"Feature","id":8,"geometry":{"type":"Point","coordinates":[40.5,-21.6000000014901]},"properties":{"OBJECTID":8,"STORMNAME":"Dikeledi","STORMTYPE":" ","ADVDATE":1736495700000,"ADVISNUM":" ","STORMNUM":7,"FCSTPRD":120,"BASIN":"SH","LAT":-21.6,"LON":40.5,"VALIDTIME":"15/0600","TAU":0,"MAXWIND":65,"GUST":0,"MSLP":9999,"TCDVLP":"Hurricane","DVLBL":"H","SSNUM":1,"TCDIR":9999,"TCSPD":9999,"DATELBL":"06:00 AM Wed","FLDATELBL":"2025-01-15 06:00 AM Wed UTC","TIMEZONE":"UTC","STORMSRC":" "}}]}